yaex/__init__.py
yaex/commands.py
yaex-1.0.0.dist-info/LICENSE
yaex-1.0.0.dist-info/WHEEL
yaex-1.0.0.dist-info/METADATA
yaex-1.0.0.dist-info/RECORD
