Metadata-Version: 2.1
Name: yaex
Version: 1.0.0
Summary: This is a library based on the ex command.
Home-page: https://github.com/emersonmx/yaex
License: MIT
Author: Emerson Max de Medeiros Silva
Author-email: emersonmx@gmail.com
Requires-Python: >=3.10,<4.0
Classifier: License :: OSI Approved :: MIT License
Classifier: Programming Language :: Python :: 3
Classifier: Programming Language :: Python :: 3.10
Project-URL: Repository, https://github.com/emersonmx/yaex
